fastpyx.cp312-win_amd64.pyd
fastpyx-0.5.4.dist-info/METADATA
fastpyx-0.5.4.dist-info/WHEEL
fastpyx-0.5.4.dist-info/top_level.txt
fastpyx-0.5.4.dist-info/RECORD
