Metadata-Version: 2.1
Name: fastpyx
Version: 0.5.4
Summary: A fast memory optimization extension for Python
Author: Mohammad Hasan Khoddami
Author-email: mohammadh.khoddami@gmail.com
License: MIT
Classifier: Programming Language :: Python :: 3
Classifier: License :: OSI Approved :: MIT License
Classifier: Operating System :: OS Independent
Requires-Python: >=3.6
